meltano_tap_cratedb-0.0.0.dist-info/licenses/LICENSE
tap_cratedb/__init__.py
tap_cratedb/client.py
tap_cratedb/patch.py
tap_cratedb/tap.py
meltano_tap_cratedb-0.0.0.dist-info/METADATA
meltano_tap_cratedb-0.0.0.dist-info/WHEEL
meltano_tap_cratedb-0.0.0.dist-info/entry_points.txt
meltano_tap_cratedb-0.0.0.dist-info/top_level.txt
meltano_tap_cratedb-0.0.0.dist-info/RECORD
