Metadata-Version: 2.4
Name: meltano-tap-cratedb
Version: 0.0.0
Summary: A Singer tap / Meltano extractor for CrateDB, built with the Meltano SDK, and based on the Meltano PostgreSQL tap.
Author-email: CrateDB Engineering <office@crate.io>
Project-URL: changelog, https://github.com/crate/meltano-tap-cratedb/blob/main/CHANGES.md
Project-URL: documentation, https://github.com/crate/meltano-tap-cratedb
Project-URL: homepage, https://github.com/crate/meltano-tap-cratedb
Project-URL: repository, https://github.com/crate/meltano-tap-cratedb
Keywords: CrateDB,data-loading,data-processing,data-toolkit,data-transfer,data-transformation,ELT,ETL,io,Meltano,Meltano SDK,PostgreSQL,Singer
Classifier: Development Status :: 3 - Alpha
Classifier: Environment :: Console
Classifier: Intended Audience :: Customer Service
Classifier: Intended Audience :: Developers
Classifier: Intended Audience :: Education
Classifier: Intended Audience :: End Users/Desktop
Classifier: Intended Audience :: Information Technology
Classifier: Intended Audience :: Manufacturing
Classifier: Intended Audience :: Science/Research
Classifier: Intended Audience :: System Administrators
Classifier: Intended Audience :: Telecommunications Industry
Classifier: Operating System :: MacOS :: MacOS X
Classifier: Operating System :: Microsoft :: Windows
Classifier: Operating System :: POSIX :: Linux
Classifier: Operating System :: Unix
Classifier: Programming Language :: Python
Classifier: Programming Language :: Python :: 3 :: Only
Classifier: Programming Language :: Python :: 3.8
Classifier: Programming Language :: Python :: 3.9
Classifier: Programming Language :: Python :: 3.10
Classifier: Programming Language :: Python :: 3.11
Classifier: Topic :: Adaptive Technologies
Classifier: Topic :: Communications
Classifier: Topic :: Database
Classifier: Topic :: Documentation
Classifier: Topic :: Education
Classifier: Topic :: Internet
Classifier: Topic :: Office/Business
Classifier: Topic :: Scientific/Engineering
Classifier: Topic :: Software Development :: Libraries
Classifier: Topic :: Software Development :: Pre-processors
Classifier: Topic :: Software Development :: Quality Assurance
Classifier: Topic :: Software Development :: Testing
Classifier: Topic :: Software Development :: Version Control
Classifier: Topic :: System :: Archiving
Classifier: Topic :: System :: Benchmark
Classifier: Topic :: System :: Clustering
Classifier: Topic :: System :: Distributed Computing
Classifier: Topic :: System :: Logging
Classifier: Topic :: System :: Monitoring
Classifier: Topic :: System :: Networking
Classifier: Topic :: System :: Systems Administration
Classifier: Topic :: Text Processing
Classifier: Topic :: Utilities
Requires-Python: <3.12,>=3.8
License-File: LICENSE
Requires-Dist: crate[sqlalchemy]<1,>=0.34
Requires-Dist: cratedb-toolkit<0.0.42
Requires-Dist: importlib-resources; python_version < "3.9"
Requires-Dist: meltanolabs-tap-postgres==0.0.6
Provides-Extra: develop
Requires-Dist: black<24; extra == "develop"
Requires-Dist: mypy==1.7.1; extra == "develop"
Requires-Dist: poethepoet<1; extra == "develop"
Requires-Dist: pyproject-fmt<2; extra == "develop"
Requires-Dist: ruff<0.15; extra == "develop"
Requires-Dist: validate-pyproject<1; extra == "develop"
Provides-Extra: release
Requires-Dist: build<2; extra == "release"
Requires-Dist: twine<5; extra == "release"
Provides-Extra: test
Requires-Dist: faker<21.0.0,>=18.5.1; extra == "test"
Requires-Dist: pendulum~=2.1; extra == "test"
Requires-Dist: pytest<8; extra == "test"
Requires-Dist: pytest-cov<5; extra == "test"
Requires-Dist: pytest-mock<4; extra == "test"
Requires-Dist: singer-sdk[testing]; extra == "test"
Dynamic: license-file
